{
  "id": "94o5QYqgxo0",
  "title": "「Beyond the Time」 Anime MV 【Gundam Char's Counterattack】 Ending Theme (Subtitles)",
  "author": "Newtypelab",
  "duration": "00:05:31",
  "detail": {
    "Id": {
      "Value": "94o5QYqgxo0"
    },
    "Url": "https://www.youtube.com/watch?v=94o5QYqgxo0",
    "Title": "「Beyond the Time」 Anime MV 【Gundam Char's Counterattack】 Ending Theme (Subtitles)",
    "Author": {
      "ChannelId": {
        "Value": "UCmuQIIWEbjfg700bw8lNcgQ"
      },
      "ChannelUrl": "https://www.youtube.com/channel/UCmuQIIWEbjfg700bw8lNcgQ",
      "ChannelTitle": "Newtypelab",
      "Title": "Newtypelab"
    },
    "UploadDate": {
      "DateTime": "2021-06-22T11:58:47.0000000",
      "UtcDateTime": "2021-06-22T18:58:47.0000000Z",
      "LocalDateTime": "2021-06-23T03:58:47.0000000+09:00",
      "Date": "2021-06-22T00:00:00.0000000",
      "Day": 22,
      "DayOfWeek": "Tuesday",
      "DayOfYear": 173,
      "Hour": 11,
      "Millisecond": 0,
      "Minute": 58,
      "Month": 6,
      "Offset": "-07:00:00",
      "Second": 47,
      "Ticks": 637599599270000000,
      "UtcTicks": 637599851270000000,
      "TimeOfDay": "11:58:47",
      "Year": 2021
    },
    "Description": "Beyond The Time by TM Network \nMobile Suit Gundam Char's Counterattack - Theme Song",
    "Duration": "00:05:31",
    "Thumbnails": [
      {
        "Url": "https://i.ytimg.com/vi/94o5QYqgxo0/hqdefault.jpg?sqp=-oaymwEbCKgBEF5IVfKriqkDDggBFQAAiEIYAXABwAEG&rs=AOn4CLAikXiSnCPUqWHUAD4B_A34s5sNgQ",
        "Resolution": {
          "Width": 168,
          "Height": 94,
          "Area": 15792
        }
      },
      {
        "Url": "https://i.ytimg.com/vi/94o5QYqgxo0/hqdefault.jpg?sqp=-oaymwEbCMQBEG5IVfKriqkDDggBFQAAiEIYAXABwAEG&rs=AOn4CLCR4tb2hWB_kjt3Ax3Bty6L_Uxu6g",
        "Resolution": {
          "Width": 196,
          "Height": 110,
          "Area": 21560
        }
      },
      {
        "Url": "https://i.ytimg.com/vi/94o5QYqgxo0/hqdefault.jpg?sqp=-oaymwEcCPYBEIoBSFXyq4qpAw4IARUAAIhCGAFwAcABBg==&rs=AOn4CLCYi0so_c0VoseTyk9CKPv60uqL6g",
        "Resolution": {
          "Width": 246,
          "Height": 138,
          "Area": 33948
        }
      },
      {
        "Url": "https://i.ytimg.com/vi/94o5QYqgxo0/hqdefault.jpg?sqp=-oaymwEcCNACELwBSFXyq4qpAw4IARUAAIhCGAFwAcABBg==&rs=AOn4CLDxHfjx_skNrf0amnujd5LsudiMxQ",
        "Resolution": {
          "Width": 336,
          "Height": 188,
          "Area": 63168
        }
      },
      {
        "Url": "https://i.ytimg.com/vi_webp/94o5QYqgxo0/maxresdefault.webp",
        "Resolution": {
          "Width": 1920,
          "Height": 1080,
          "Area": 2073600
        }
      },
      {
        "Url": "https://img.youtube.com/vi/94o5QYqgxo0/default.jpg",
        "Resolution": {
          "Width": 120,
          "Height": 90,
          "Area": 10800
        }
      },
      {
        "Url": "https://img.youtube.com/vi/94o5QYqgxo0/mqdefault.jpg",
        "Resolution": {
          "Width": 320,
          "Height": 180,
          "Area": 57600
        }
      },
      {
        "Url": "https://img.youtube.com/vi/94o5QYqgxo0/hqdefault.jpg",
        "Resolution": {
          "Width": 480,
          "Height": 360,
          "Area": 172800
        }
      }
    ],
    "Keywords": [
      "beyond the time gundam",
      "gundam beyond the time",
      "beyond the time amv",
      "gundam amv",
      "gundam beyond the time amv",
      "gundam cca ending",
      "gundam cca amv",
      "gundam char counter",
      "gundam char counter amv",
      "gundam char's amv",
      "gundam chars ending",
      "gundam legendado",
      "gundam chars legendado",
      "gundam chars netflix",
      "gundam netflix"
    ],
    "Engagement": {
      "ViewCount": 16493794,
      "LikeCount": 73676,
      "DislikeCount": 0,
      "AverageRating": 5
    }
  }
}
