{
  "id": "DkTuNkFZC_w",
  "title": "「銀河鉄道999 / ゴダイゴ」を乃木坂46風にアレンジしたら【AIカバー】",
  "author": "HRK",
  "duration": "00:03:05",
  "detail": {
    "Id": {
      "Value": "DkTuNkFZC_w"
    },
    "Url": "https://www.youtube.com/watch?v=DkTuNkFZC_w",
    "Title": "「銀河鉄道999 / ゴダイゴ」を乃木坂46風にアレンジしたら【AIカバー】",
    "Author": {
      "ChannelId": {
        "Value": "UC2VrYhOdS0roQjFMwLPfSXA"
      },
      "ChannelUrl": "https://www.youtube.com/channel/UC2VrYhOdS0roQjFMwLPfSXA",
      "ChannelTitle": "HRK",
      "Title": "HRK"
    },
    "UploadDate": {
      "DateTime": "2026-01-01T18:00:12.0000000",
      "UtcDateTime": "2026-01-02T02:00:12.0000000Z",
      "LocalDateTime": "2026-01-02T11:00:12.0000000+09:00",
      "Date": "2026-01-01T00:00:00.0000000",
      "Day": 1,
      "DayOfWeek": "Thursday",
      "DayOfYear": 1,
      "Hour": 18,
      "Millisecond": 0,
      "Minute": 0,
      "Month": 1,
      "Offset": "-08:00:00",
      "Second": 12,
      "Ticks": 639028872120000000,
      "UtcTicks": 639029160120000000,
      "TimeOfDay": "18:00:12",
      "Year": 2026
    },
    "Description": "時代や世代を越えて愛され続けるゴダイゴの名曲をカバーしました。\n聴く人それぞれの記憶や情景と重なりながらこの曲が今も走り続けていることを感じてもらえたら嬉しいです。\n\n※本動画は非公式のカバーです。公式・原作者・関係各所とは一切関係ありません。\n\n▼HRK グッズ\nhttps://suzuri.jp/HRKSHOP/products\n\n▼絵画販売\nhttps://itokazu1110.official.ec/\n\n▼Instagram（Draw）\nhttps://www.instagram.com/pen_hero_japan/",
    "Duration": "00:03:05",
    "Thumbnails": [
      {
        "Url": "https://i.ytimg.com/vi/DkTuNkFZC_w/hqdefault.jpg?sqp=-oaymwE1CKgBEF5IVfKriqkDKAgBFQAAiEIYAXABwAEG8AEB-AH-CYAC0AWKAgwIABABGF8gRyhlMA8=&rs=AOn4CLAYWGRwExnisnt9FgOUVV0xMEZZrw",
        "Resolution": {
          "Width": 168,
          "Height": 94,
          "Area": 15792
        }
      },
      {
        "Url": "https://i.ytimg.com/vi/DkTuNkFZC_w/hqdefault.jpg?sqp=-oaymwE1CMQBEG5IVfKriqkDKAgBFQAAiEIYAXABwAEG8AEB-AH-CYAC0AWKAgwIABABGF8gRyhlMA8=&rs=AOn4CLAqC9wezxOMOC6oOgTGJc5wtLIN0Q",
        "Resolution": {
          "Width": 196,
          "Height": 110,
          "Area": 21560
        }
      },
      {
        "Url": "https://i.ytimg.com/vi/DkTuNkFZC_w/hqdefault.jpg?sqp=-oaymwE2CPYBEIoBSFXyq4qpAygIARUAAIhCGAFwAcABBvABAfgB_gmAAtAFigIMCAAQARhfIEcoZTAP&rs=AOn4CLArbHTkjjJ0F5FrUUPYKtCyLFwZ-w",
        "Resolution": {
          "Width": 246,
          "Height": 138,
          "Area": 33948
        }
      },
      {
        "Url": "https://i.ytimg.com/vi/DkTuNkFZC_w/hqdefault.jpg?sqp=-oaymwE2CNACELwBSFXyq4qpAygIARUAAIhCGAFwAcABBvABAfgB_gmAAtAFigIMCAAQARhfIEcoZTAP&rs=AOn4CLCkCCdWQTyMcGPyNw3AiLNxmfxTNA",
        "Resolution": {
          "Width": 336,
          "Height": 188,
          "Area": 63168
        }
      },
      {
        "Url": "https://i.ytimg.com/vi/DkTuNkFZC_w/maxresdefault.jpg?sqp=-oaymwEmCIAKENAF8quKqQMa8AEB-AH-CYAC0AWKAgwIABABGF8gRyhlMA8=&rs=AOn4CLBQfhu3Tbgc6RJ7LThkHGHLAbc8Yg",
        "Resolution": {
          "Width": 1920,
          "Height": 1080,
          "Area": 2073600
        }
      },
      {
        "Url": "https://img.youtube.com/vi/DkTuNkFZC_w/default.jpg",
        "Resolution": {
          "Width": 120,
          "Height": 90,
          "Area": 10800
        }
      },
      {
        "Url": "https://img.youtube.com/vi/DkTuNkFZC_w/mqdefault.jpg",
        "Resolution": {
          "Width": 320,
          "Height": 180,
          "Area": 57600
        }
      },
      {
        "Url": "https://img.youtube.com/vi/DkTuNkFZC_w/hqdefault.jpg",
        "Resolution": {
          "Width": 480,
          "Height": 360,
          "Area": 172800
        }
      }
    ],
    "Keywords": [
      "銀河鉄道999",
      "Galaxy Express 999",
      "ゴダイゴ",
      "GODIEGO",
      "松本零士",
      "アニソン",
      "アニメソング",
      "昭和アニメ",
      "昭和歌謡",
      "70年代JPOP",
      "名曲カバー",
      "女性ボーカル",
      "アイドルカバー",
      "AIカバー",
      "JPOPカバー",
      "日本の名曲",
      "懐メロ",
      "名曲リメイク",
      "非公式カバー"
    ],
    "Engagement": {
      "ViewCount": 233493,
      "LikeCount": 3516,
      "DislikeCount": 0,
      "AverageRating": 5
    }
  }
}
