{
  "id": "g8BKDAzk_zA",
  "title": "\"パラダイス銀河\" 放課後女子高生バンドがメタルカバーしてみた | 光GENJI",
  "author": "Cover Music",
  "duration": "00:04:43",
  "detail": {
    "Id": {
      "Value": "g8BKDAzk_zA"
    },
    "Url": "https://www.youtube.com/watch?v=g8BKDAzk_zA",
    "Title": "\"パラダイス銀河\" 放課後女子高生バンドがメタルカバーしてみた | 光GENJI",
    "Author": {
      "ChannelId": {
        "Value": "UCcfweKYj2PeI9u_MeczAPTQ"
      },
      "ChannelUrl": "https://www.youtube.com/channel/UCcfweKYj2PeI9u_MeczAPTQ",
      "ChannelTitle": "Cover Music",
      "Title": "Cover Music"
    },
    "UploadDate": {
      "DateTime": "2026-01-29T01:00:54.0000000",
      "UtcDateTime": "2026-01-29T09:00:54.0000000Z",
      "LocalDateTime": "2026-01-29T18:00:54.0000000+09:00",
      "Date": "2026-01-29T00:00:00.0000000",
      "Day": 29,
      "DayOfWeek": "Thursday",
      "DayOfYear": 29,
      "Hour": 1,
      "Millisecond": 0,
      "Minute": 0,
      "Month": 1,
      "Offset": "-08:00:00",
      "Second": 54,
      "Ticks": 639052452540000000,
      "UtcTicks": 639052740540000000,
      "TimeOfDay": "01:00:54",
      "Year": 2026
    },
    "Description": "#aicover \n#光genji \n#metalcover \n\nオリジナル\nhttps://youtu.be/XFGWYi_cAx4?si=yKGK2Uy6I8ZVX9Jb",
    "Duration": "00:04:43",
    "Thumbnails": [
      {
        "Url": "https://i.ytimg.com/vi/g8BKDAzk_zA/hqdefault.jpg?sqp=-oaymwE1CKgBEF5IVfKriqkDKAgBFQAAiEIYAXABwAEG8AEB-AH-CYAC0AWKAgwIABABGHIgVSg6MA8=&rs=AOn4CLBPVmFORtJ5CWyaZJc_lrPn0-H-UQ",
        "Resolution": {
          "Width": 168,
          "Height": 94,
          "Area": 15792
        }
      },
      {
        "Url": "https://i.ytimg.com/vi/g8BKDAzk_zA/hqdefault.jpg?sqp=-oaymwE1CMQBEG5IVfKriqkDKAgBFQAAiEIYAXABwAEG8AEB-AH-CYAC0AWKAgwIABABGHIgVSg6MA8=&rs=AOn4CLDaNC6-zcg4n7bmHqgS5j9RT5K7GA",
        "Resolution": {
          "Width": 196,
          "Height": 110,
          "Area": 21560
        }
      },
      {
        "Url": "https://i.ytimg.com/vi/g8BKDAzk_zA/hqdefault.jpg?sqp=-oaymwE2CPYBEIoBSFXyq4qpAygIARUAAIhCGAFwAcABBvABAfgB_gmAAtAFigIMCAAQARhyIFUoOjAP&rs=AOn4CLDrTAKi8RoKkBF8qegLMlY3CHRXTg",
        "Resolution": {
          "Width": 246,
          "Height": 138,
          "Area": 33948
        }
      },
      {
        "Url": "https://i.ytimg.com/vi/g8BKDAzk_zA/hqdefault.jpg?sqp=-oaymwE2CNACELwBSFXyq4qpAygIARUAAIhCGAFwAcABBvABAfgB_gmAAtAFigIMCAAQARhyIFUoOjAP&rs=AOn4CLA6fADbEksrbkEL9p3zLGoFDd5-qQ",
        "Resolution": {
          "Width": 336,
          "Height": 188,
          "Area": 63168
        }
      },
      {
        "Url": "https://i.ytimg.com/vi/g8BKDAzk_zA/maxresdefault.jpg?sqp=-oaymwEmCIAKENAF8quKqQMa8AEB-AH-CYAC0AWKAgwIABABGHIgVSg6MA8=&rs=AOn4CLDMJ0uuraMy_d2PiCx5N9AWcd-U0Q",
        "Resolution": {
          "Width": 1920,
          "Height": 1080,
          "Area": 2073600
        }
      },
      {
        "Url": "https://img.youtube.com/vi/g8BKDAzk_zA/default.jpg",
        "Resolution": {
          "Width": 120,
          "Height": 90,
          "Area": 10800
        }
      },
      {
        "Url": "https://img.youtube.com/vi/g8BKDAzk_zA/mqdefault.jpg",
        "Resolution": {
          "Width": 320,
          "Height": 180,
          "Area": 57600
        }
      },
      {
        "Url": "https://img.youtube.com/vi/g8BKDAzk_zA/hqdefault.jpg",
        "Resolution": {
          "Width": 480,
          "Height": 360,
          "Area": 172800
        }
      }
    ],
    "Keywords": [
      "CITYPOPS",
      "JPOP",
      "RETRO",
      "80s",
      "1980s",
      "昭和",
      "平成",
      "レトロ",
      "80年代",
      "BGM",
      "citypop",
      "jpop"
    ],
    "Engagement": {
      "ViewCount": 64624,
      "LikeCount": 632,
      "DislikeCount": 0,
      "AverageRating": 5
    }
  }
}
