{
  "id": "NmuqoLeb6tE",
  "title": "ひとり上手",
  "author": "HiREN 【UTAHIME DREAM】 (CV:Kaya) - Topic",
  "duration": "00:04:14",
  "detail": {
    "Id": {
      "Value": "NmuqoLeb6tE"
    },
    "Url": "https://www.youtube.com/watch?v=NmuqoLeb6tE",
    "Title": "ひとり上手",
    "Author": {
      "ChannelId": {
        "Value": "UCari3gmrrei-AC2o9idHmtw"
      },
      "ChannelUrl": "https://www.youtube.com/channel/UCari3gmrrei-AC2o9idHmtw",
      "ChannelTitle": "HiREN 【UTAHIME DREAM】 (CV:Kaya) - Topic",
      "Title": "HiREN 【UTAHIME DREAM】 (CV:Kaya) - Topic"
    },
    "UploadDate": {
      "DateTime": "2023-06-27T03:04:17.0000000",
      "UtcDateTime": "2023-06-27T10:04:17.0000000Z",
      "LocalDateTime": "2023-06-27T19:04:17.0000000+09:00",
      "Date": "2023-06-27T00:00:00.0000000",
      "Day": 27,
      "DayOfWeek": "Tuesday",
      "DayOfYear": 178,
      "Hour": 3,
      "Millisecond": 0,
      "Minute": 4,
      "Month": 6,
      "Offset": "-07:00:00",
      "Second": 17,
      "Ticks": 638234318570000000,
      "UtcTicks": 638234570570000000,
      "TimeOfDay": "03:04:17",
      "Year": 2023
    },
    "Description": "Provided to YouTube by NexTone Inc.\n\nひとり上手 · HiREN 【UTAHIME DREAM】 (CV:Kaya) · Miyuki Nakajima · Miyuki Nakajima · 百石元\n\nHitori Jozu\n\nReleased on: 2023-06-28\n\nAuto-generated by YouTube.",
    "Duration": "00:04:14",
    "Thumbnails": [
      {
        "Url": "https://i.ytimg.com/vi/NmuqoLeb6tE/hqdefault.jpg?sqp=-oaymwEbCKgBEF5IVfKriqkDDggBFQAAiEIYAXABwAEG&rs=AOn4CLAqtoGFRZ0wilr_Fy2e87bB5k9fIg",
        "Resolution": {
          "Width": 168,
          "Height": 94,
          "Area": 15792
        }
      },
      {
        "Url": "https://i.ytimg.com/vi/NmuqoLeb6tE/hqdefault.jpg?sqp=-oaymwEbCMQBEG5IVfKriqkDDggBFQAAiEIYAXABwAEG&rs=AOn4CLDEtuZ0GMxW1tcUGh1np4eX0MDznA",
        "Resolution": {
          "Width": 196,
          "Height": 110,
          "Area": 21560
        }
      },
      {
        "Url": "https://i.ytimg.com/vi/NmuqoLeb6tE/hqdefault.jpg?sqp=-oaymwEcCPYBEIoBSFXyq4qpAw4IARUAAIhCGAFwAcABBg==&rs=AOn4CLCokYHf8dSwNKF4dUydUrJRHkYnRQ",
        "Resolution": {
          "Width": 246,
          "Height": 138,
          "Area": 33948
        }
      },
      {
        "Url": "https://i.ytimg.com/vi/NmuqoLeb6tE/hqdefault.jpg?sqp=-oaymwEcCNACELwBSFXyq4qpAw4IARUAAIhCGAFwAcABBg==&rs=AOn4CLDSrrle7jFr7ro4tmskjEEunQM-LA",
        "Resolution": {
          "Width": 336,
          "Height": 188,
          "Area": 63168
        }
      },
      {
        "Url": "https://i.ytimg.com/vi/NmuqoLeb6tE/maxresdefault.jpg",
        "Resolution": {
          "Width": 1920,
          "Height": 1080,
          "Area": 2073600
        }
      },
      {
        "Url": "https://img.youtube.com/vi/NmuqoLeb6tE/default.jpg",
        "Resolution": {
          "Width": 120,
          "Height": 90,
          "Area": 10800
        }
      },
      {
        "Url": "https://img.youtube.com/vi/NmuqoLeb6tE/mqdefault.jpg",
        "Resolution": {
          "Width": 320,
          "Height": 180,
          "Area": 57600
        }
      },
      {
        "Url": "https://img.youtube.com/vi/NmuqoLeb6tE/hqdefault.jpg",
        "Resolution": {
          "Width": 480,
          "Height": 360,
          "Area": 172800
        }
      }
    ],
    "Keywords": [
      "HiREN 【UTAHIME DREAM】 (CV:Kaya)",
      "HiREN 【ウタヒメドリーム】 (CV:花耶)",
      "Miyuki Nakajima",
      "中島みゆき",
      "百石元",
      "Hitori Jozu"
    ],
    "Engagement": {
      "ViewCount": 637045,
      "LikeCount": 4385,
      "DislikeCount": 0,
      "AverageRating": 5
    }
  }
}
