{
  "id": "qgHlUeOkAo4",
  "title": "[뮤뱅 원테이크 4K] 트와이스(TWICE) 'Strategy' 4K Bonus Ver. @뮤직뱅크 (Music Bank) 241206",
  "author": "KBS Kpop",
  "duration": "00:03:09",
  "detail": {
    "Id": {
      "Value": "qgHlUeOkAo4"
    },
    "Url": "https://www.youtube.com/watch?v=qgHlUeOkAo4",
    "Title": "[뮤뱅 원테이크 4K] 트와이스(TWICE) 'Strategy' 4K Bonus Ver. @뮤직뱅크 (Music Bank) 241206",
    "Author": {
      "ChannelId": {
        "Value": "UCeLPm9yH_a_QH8n6445G-Ow"
      },
      "ChannelUrl": "https://www.youtube.com/channel/UCeLPm9yH_a_QH8n6445G-Ow",
      "ChannelTitle": "KBS Kpop",
      "Title": "KBS Kpop"
    },
    "UploadDate": {
      "DateTime": "2024-12-06T02:01:01.0000000",
      "UtcDateTime": "2024-12-06T10:01:01.0000000Z",
      "LocalDateTime": "2024-12-06T19:01:01.0000000+09:00",
      "Date": "2024-12-06T00:00:00.0000000",
      "Day": 6,
      "DayOfWeek": "Friday",
      "DayOfYear": 341,
      "Hour": 2,
      "Millisecond": 0,
      "Minute": 1,
      "Month": 12,
      "Offset": "-08:00:00",
      "Second": 1,
      "Ticks": 638690472610000000,
      "UtcTicks": 638690760610000000,
      "TimeOfDay": "02:01:01",
      "Year": 2024
    },
    "Description": "#TWICE #트와이스 #Strategy #원테이크 #원테이크4K\n\nMore from #KBSKPOP\n\nTwitter:       https://twitter.com/StudioK_twt\nInstagram: https://www.instagram.com/kbs_kpop_official",
    "Duration": "00:03:09",
    "Thumbnails": [
      {
        "Url": "https://i.ytimg.com/vi/qgHlUeOkAo4/hqdefault.jpg?sqp=-oaymwEbCKgBEF5IVfKriqkDDggBFQAAiEIYAXABwAEG&rs=AOn4CLAiTfiOjNjhV-aAOlMXCqAmRJAkyg",
        "Resolution": {
          "Width": 168,
          "Height": 94,
          "Area": 15792
        }
      },
      {
        "Url": "https://i.ytimg.com/vi/qgHlUeOkAo4/hqdefault.jpg?sqp=-oaymwEbCMQBEG5IVfKriqkDDggBFQAAiEIYAXABwAEG&rs=AOn4CLApqvMqnjQ37l7G3CpiqSVN-1LX3A",
        "Resolution": {
          "Width": 196,
          "Height": 110,
          "Area": 21560
        }
      },
      {
        "Url": "https://i.ytimg.com/vi/qgHlUeOkAo4/hqdefault.jpg?sqp=-oaymwEcCPYBEIoBSFXyq4qpAw4IARUAAIhCGAFwAcABBg==&rs=AOn4CLD1H32kJ768a34ye3uOMO90nHC3yA",
        "Resolution": {
          "Width": 246,
          "Height": 138,
          "Area": 33948
        }
      },
      {
        "Url": "https://i.ytimg.com/vi/qgHlUeOkAo4/hqdefault.jpg?sqp=-oaymwEcCNACELwBSFXyq4qpAw4IARUAAIhCGAFwAcABBg==&rs=AOn4CLC9flwBL45L195I1ZlnMYcjAdjK_w",
        "Resolution": {
          "Width": 336,
          "Height": 188,
          "Area": 63168
        }
      },
      {
        "Url": "https://i.ytimg.com/vi_webp/qgHlUeOkAo4/maxresdefault.webp",
        "Resolution": {
          "Width": 1920,
          "Height": 1080,
          "Area": 2073600
        }
      },
      {
        "Url": "https://img.youtube.com/vi/qgHlUeOkAo4/default.jpg",
        "Resolution": {
          "Width": 120,
          "Height": 90,
          "Area": 10800
        }
      },
      {
        "Url": "https://img.youtube.com/vi/qgHlUeOkAo4/mqdefault.jpg",
        "Resolution": {
          "Width": 320,
          "Height": 180,
          "Area": 57600
        }
      },
      {
        "Url": "https://img.youtube.com/vi/qgHlUeOkAo4/hqdefault.jpg",
        "Resolution": {
          "Width": 480,
          "Height": 360,
          "Area": 172800
        }
      }
    ],
    "Keywords": [
      "KBS",
      "KPOP",
      "뮤직",
      "KBSKPOP",
      "K-POP",
      "케이팝",
      "kpop",
      "KBSKpop",
      "음악",
      "kbs kpop",
      "트와이스 뮤뱅",
      "트와이스 뮤직뱅크",
      "트와이스 직캠",
      "twice fancam",
      "나연",
      "정연",
      "모모",
      "사나",
      "지효",
      "미나",
      "다현",
      "채영",
      "쯔위",
      "NAYEON ナヨン",
      "JEONGYEON ジョンヨン",
      "MOMO モモ",
      "SANA サナ",
      "JIHYO ジヒョ",
      "MINA ミナ",
      "DAHYUN ダヒョン",
      "CHAEYOUNG チェヨン",
      "아이돌 직캠",
      "idol fancam",
      "dance idol",
      "twice 무대",
      "TZUYU ツウィ",
      "kbs kpop idol twice",
      "musicbank fancam",
      "kbs fancam",
      "트와이스",
      "xmdhkdltm",
      "뮤뱅 트와이스",
      "twice",
      "twice Strategy musicbank",
      "뮤뱅 Strategy",
      "뮤뱅 트와이스 무대",
      "Strategy",
      "뮤뱅 원테이크 Strategy",
      "MUSICBANK TWICE strategy"
    ],
    "Engagement": {
      "ViewCount": 15223363,
      "LikeCount": 224836,
      "DislikeCount": 0,
      "AverageRating": 5
    }
  }
}
