{
  "id": "r0h98ZLc9yY",
  "title": "[SEOUL SPRING FESTA Wonder Show 2025] TWS - Countdown!, Plot Twist | KBS WORLD TV 250504",
  "author": "KBS WORLD Indonesian",
  "duration": "00:05:49",
  "detail": {
    "Id": {
      "Value": "r0h98ZLc9yY"
    },
    "Url": "https://www.youtube.com/watch?v=r0h98ZLc9yY",
    "Title": "[SEOUL SPRING FESTA Wonder Show 2025] TWS - Countdown!, Plot Twist | KBS WORLD TV 250504",
    "Author": {
      "ChannelId": {
        "Value": "UC72Yq2bhmBDkpvm6F0pSH4Q"
      },
      "ChannelUrl": "https://www.youtube.com/channel/UC72Yq2bhmBDkpvm6F0pSH4Q",
      "ChannelTitle": "KBS WORLD Indonesian",
      "Title": "KBS WORLD Indonesian"
    },
    "UploadDate": {
      "DateTime": "2025-06-15T06:01:23.0000000",
      "UtcDateTime": "2025-06-15T13:01:23.0000000Z",
      "LocalDateTime": "2025-06-15T22:01:23.0000000+09:00",
      "Date": "2025-06-15T00:00:00.0000000",
      "Day": 15,
      "DayOfWeek": "Sunday",
      "DayOfYear": 166,
      "Hour": 6,
      "Millisecond": 0,
      "Minute": 1,
      "Month": 6,
      "Offset": "-07:00:00",
      "Second": 23,
      "Ticks": 638855640830000000,
      "UtcTicks": 638855892830000000,
      "TimeOfDay": "06:01:23",
      "Year": 2025
    },
    "Description": "#SeoulSpringFest2025 #WonderShow #서울스프링페스타2025 #원더쇼\n#Countdown #PlotTwist #TWS #투어스\n\nSubscribe channel KBS World Indonesian supaya tidak ketinggalan konten terbaru dari kami!\nLike, Share, dan Comment kalian juga sangat berarti bagi kami! \nJika subtitle tidak terlihat, sentuh tombol [CC] di bagian bawah video! \nUntuk smartphone: sentuh video, sentuh menu (ikon titik tiga vertikal) di bagian kanan atas video, pilih Captions, lalu pilih Indonesian.\n\nHak Cipta ⓒ KBS. Dilarang menyalin, mendistribusikan, dan menggunakan konten kami (termasuk penggunaan data AI) \n\n☆Subscribe KBS WORLD Official Pages☆\n\n▶YouTube :\nhttps://www.youtube.com/kbsindonesian\n\n▶Homepage: \nhttps://world.kbs.co.kr/indonesian\n\n▶Instagram: \nhttps://www.instagram.com/kbsindonesian\n\n▶Facebook: \nhttps://www.facebook.com/kbsindonesian\n\n▶X:\nhttps://twitter.com/kbsindonesian\n\n▶ Aplikasi\n   · iOS : https://apple.co/3yQ0n7Z\n   ∙ Android : https://bit.ly/3Io5sri",
    "Duration": "00:05:49",
    "Thumbnails": [
      {
        "Url": "https://i.ytimg.com/vi/r0h98ZLc9yY/hqdefault.jpg?sqp=-oaymwEbCKgBEF5IVfKriqkDDggBFQAAiEIYAXABwAEG&rs=AOn4CLC1rwmpfdMjc-gfT7BPxYQxybcI2A",
        "Resolution": {
          "Width": 168,
          "Height": 94,
          "Area": 15792
        }
      },
      {
        "Url": "https://i.ytimg.com/vi/r0h98ZLc9yY/hqdefault.jpg?sqp=-oaymwEbCMQBEG5IVfKriqkDDggBFQAAiEIYAXABwAEG&rs=AOn4CLBGIvy1hC9LshAOGw3FRyuHVNcVOw",
        "Resolution": {
          "Width": 196,
          "Height": 110,
          "Area": 21560
        }
      },
      {
        "Url": "https://i.ytimg.com/vi/r0h98ZLc9yY/hqdefault.jpg?sqp=-oaymwEcCPYBEIoBSFXyq4qpAw4IARUAAIhCGAFwAcABBg==&rs=AOn4CLBcrbu3MIJJmGENMgvwg4kSihT2oQ",
        "Resolution": {
          "Width": 246,
          "Height": 138,
          "Area": 33948
        }
      },
      {
        "Url": "https://i.ytimg.com/vi/r0h98ZLc9yY/hqdefault.jpg?sqp=-oaymwEcCNACELwBSFXyq4qpAw4IARUAAIhCGAFwAcABBg==&rs=AOn4CLCZORNrL6Gvc-VaIYhNPWU3iVvb4Q",
        "Resolution": {
          "Width": 336,
          "Height": 188,
          "Area": 63168
        }
      },
      {
        "Url": "https://i.ytimg.com/vi_webp/r0h98ZLc9yY/maxresdefault.webp",
        "Resolution": {
          "Width": 1920,
          "Height": 1080,
          "Area": 2073600
        }
      },
      {
        "Url": "https://img.youtube.com/vi/r0h98ZLc9yY/default.jpg",
        "Resolution": {
          "Width": 120,
          "Height": 90,
          "Area": 10800
        }
      },
      {
        "Url": "https://img.youtube.com/vi/r0h98ZLc9yY/mqdefault.jpg",
        "Resolution": {
          "Width": 320,
          "Height": 180,
          "Area": 57600
        }
      },
      {
        "Url": "https://img.youtube.com/vi/r0h98ZLc9yY/hqdefault.jpg",
        "Resolution": {
          "Width": 480,
          "Height": 360,
          "Area": 172800
        }
      }
    ],
    "Keywords": [
      "kbs world",
      "kbs",
      "kbs world indonesian",
      "hallyu",
      "kpop",
      "k-pop",
      "k-entertainment",
      "DRAKOR",
      "KPOP",
      "K-Varietyshow",
      "Acara TV Korea",
      "Reaksi Artis Korea",
      "Program Korea",
      "Mukbang"
    ],
    "Engagement": {
      "ViewCount": 18560,
      "LikeCount": 738,
      "DislikeCount": 0,
      "AverageRating": 5
    }
  }
}
